{
   "name":  "Query", 
   "result": 0.507255,
   "timing": 0.507255,
   "cardinality": 0,
   "extra_info": "SELECT MIN(t.title) AS complete_downey_ironman_movie\nFROM complete_cast AS cc,\n     comp_cast_type AS cct1,\n     comp_cast_type AS cct2,\n     char_name AS chn,\n     cast_info AS ci,\n     keyword AS k,\n     kind_type AS kt,\n     movie_keyword AS mk,\n     name AS n,\n     title AS t\nWHERE cct1.kind = 'cast'\n  AND cct2.kind LIKE '%complete%'\n  AND chn.name NOT LIKE '%Sherlock%'\n  AND (chn.name LIKE '%Tony%Stark%'\n       OR chn.name LIKE '%Iron%Man%')\n  AND k.keyword IN ('superhero',\n                    'sequel',\n                    'second-part',\n                    'marvel-comics',\n                    'based-on-comic',\n                    'tv-special',\n                    'fight',\n                    'violence')\n  AND kt.kind = 'movie'\n  AND t.production_year > 1950\n  AND kt.id = t.kind_id\n  AND t.id = mk.movie_id\n  AND t.id = ci.movie_id\n  AND t.id = cc.movie_id\n  AND mk.movie_id = ci.movie_id\n  AND mk.movie_id = cc.movie_id\n  AND ci.movie_id = cc.movie_id\n  AND chn.id = ci.person_role_id\n  AND n.id = ci.person_id\n  AND k.id = mk.keyword_id\n  AND cct1.id = cc.subject_id\n  AND cct2.id = cc.status_id;\n\n", 
   "timings": [
   {
   "annotation": "optimizer", 
   "timing": 0.002897
   },
   {
   "annotation": "optimizer > column_lifetime", 
   "timing": 0.000012
   },
   {
   "annotation": "optimizer > common_aggregate", 
   "timing": 0.000001
   },
   {
   "annotation": "optimizer > common_subexpressions", 
   "timing": 0.000001
   },
   {
   "annotation": "optimizer > deliminator", 
   "timing": 0.000000
   },
   {
   "annotation": "optimizer > expression_rewriter", 
   "timing": 0.000035
   },
   {
   "annotation": "optimizer > filter_pullup", 
   "timing": 0.000001
   },
   {
   "annotation": "optimizer > filter_pushdown", 
   "timing": 0.000110
   },
   {
   "annotation": "optimizer > in_clause", 
   "timing": 0.000012
   },
   {
   "annotation": "optimizer > join_order", 
   "timing": 0.002623
   },
   {
   "annotation": "optimizer > regex_range", 
   "timing": 0.000001
   },
   {
   "annotation": "optimizer > reorder_filter", 
   "timing": 0.000003
   },
   {
   "annotation": "optimizer > statistics_propagation", 
   "timing": 0.000087
   },
   {
   "annotation": "optimizer > top_n", 
   "timing": 0.000001
   },
   {
   "annotation": "optimizer > unused_columns", 
   "timing": 0.000007
   },
   {
   "annotation": "physical_planner", 
   "timing": 0.000051
   },
   {
   "annotation": "physical_planner > column_binding", 
   "timing": 0.000015
   },
   {
   "annotation": "physical_planner > create_plan", 
   "timing": 0.000024
   },
   {
   "annotation": "physical_planner > resolve_types", 
   "timing": 0.000003
   },
   {
   "annotation": "planner", 
   "timing": 0.000129
   },
   {
   "annotation": "planner > binder", 
   "timing": 0.000127
   }
   ],
   "children": [
    {
      "name": "RESULT_COLLECTOR",
      "timing":0.000002,
      "cardinality":0,
      "extra_info": "",
      "timings": [
      ],
      "children": [
       {
         "name": "SIMPLE_AGGREGATE",
         "timing":0.000003,
         "cardinality":1,
         "extra_info": "min(#0)",
         "timings": [
         ],
         "children": [
          {
            "name": "PROJECTION",
            "timing":0.000000,
            "cardinality":33,
            "extra_info": "title\n",
            "timings": [
            ],
            "children": [
             {
               "name": "HASH_JOIN",
               "timing":0.001961,
               "cardinality":33,
               "extra_info": "INNER\nid = movie_id\nmovie_id = movie_id\nmovie_id = movie_id\n",
               "timings": [
               ],
               "children": [
                {
                  "name": "HASH_JOIN",
                  "timing":0.006040,
                  "cardinality":63,
                  "extra_info": "INNER\nperson_role_id = id\n",
                  "timings": [
                  ],
                  "children": [
                   {
                     "name": "HASH_JOIN",
                     "timing":2.279789,
                     "cardinality":985102,
                     "extra_info": "INNER\nmovie_id = id\nmovie_id = movie_id\n",
                     "timings": [
                     ],
                     "children": [
                      {
                        "name": "HASH_JOIN",
                        "timing":0.559582,
                        "cardinality":36244344,
                        "extra_info": "INNER\nperson_id = id\n",
                        "timings": [
                        ],
                        "children": [
                         {
                           "name": "SEQ_SCAN",
                           "timing":0.045378,
                           "cardinality":36244344,
                           "extra_info": "cast_info\n[INFOSEPARATOR]\nmovie_id\nperson_role_id\nperson_id",
                           "timings": [
                           ],
                           "children": [
                           ]
                         }
,
                         {
                           "name": "SEQ_SCAN",
                           "timing":0.002446,
                           "cardinality":4167491,
                           "extra_info": "name\n[INFOSEPARATOR]\nid",
                           "timings": [
                           ],
                           "children": [
                           ]
                         }
                        ]
                      }
,
                      {
                        "name": "HASH_JOIN",
                        "timing":0.007969,
                        "cardinality":15994,
                        "extra_info": "INNER\nkeyword_id = id\n",
                        "timings": [
                        ],
                        "children": [
                         {
                           "name": "HASH_JOIN",
                           "timing":0.011299,
                           "cardinality":2343162,
                           "extra_info": "INNER\nkind_id = id\n",
                           "timings": [
                           ],
                           "children": [
                            {
                              "name": "HASH_JOIN",
                              "timing":0.211760,
                              "cardinality":3961736,
                              "extra_info": "INNER\nmovie_id = id\n",
                              "timings": [
                              ],
                              "children": [
                               {
                                 "name": "SEQ_SCAN",
                                 "timing":0.002255,
                                 "cardinality":4523930,
                                 "extra_info": "movie_keyword\n[INFOSEPARATOR]\nmovie_id\nkeyword_id",
                                 "timings": [
                                 ],
                                 "children": [
                                 ]
                               }
,
                               {
                                 "name": "SEQ_SCAN",
                                 "timing":0.048112,
                                 "cardinality":2287271,
                                 "extra_info": "title\n[INFOSEPARATOR]\nproduction_year\nkind_id\nid\ntitle\n[INFOSEPARATOR]\nFilters: production_year>1950 AND production_year IS NOT NULL\n",
                                 "timings": [
                                 ],
                                 "children": [
                                 ]
                               }
                              ]
                            }
,
                            {
                              "name": "SEQ_SCAN",
                              "timing":0.000006,
                              "cardinality":1,
                              "extra_info": "kind_type\n[INFOSEPARATOR]\nkind\nid\n[INFOSEPARATOR]\nFilters: kind=movie AND kind IS NOT NULL\n",
                              "timings": [
                              ],
                              "children": [
                              ]
                            }
                           ]
                         }
,
                         {
                           "name": "PROJECTION",
                           "timing":0.000001,
                           "cardinality":8,
                           "extra_info": "#1\n",
                           "timings": [
                           ],
                           "children": [
                            {
                              "name": "FILTER",
                              "timing":0.000103,
                              "cardinality":8,
                              "extra_info": "IN (...)",
                              "timings": [
                              ],
                              "children": [
                               {
                                 "name": "HASH_JOIN",
                                 "timing":0.002707,
                                 "cardinality":134170,
                                 "extra_info": "MARK\nkeyword = #0\n",
                                 "timings": [
                                 ],
                                 "children": [
                                  {
                                    "name": "SEQ_SCAN",
                                    "timing":0.001225,
                                    "cardinality":134170,
                                    "extra_info": "keyword\n[INFOSEPARATOR]\nkeyword\nid",
                                    "timings": [
                                    ],
                                    "children": [
                                    ]
                                  }
,
                                  {
                                    "name": "CHUNK_SCAN",
                                    "timing":0.000001,
                                    "cardinality":8,
                                    "extra_info": "",
                                    "timings": [
                                    ],
                                    "children": [
                                    ]
                                  }
                                 ]
                               }
                              ]
                            }
                           ]
                         }
                        ]
                      }
                     ]
                   }
,
                   {
                     "name": "PROJECTION",
                     "timing":0.000005,
                     "cardinality":30,
                     "extra_info": "#1\n",
                     "timings": [
                     ],
                     "children": [
                      {
                        "name": "FILTER",
                        "timing":0.119916,
                        "cardinality":30,
                        "extra_info": "(((name ~~ '%Tony%Stark%') OR (name ~~ '%Iron%Man%')) AND NOT(contains(name, 'Sherlock')))",
                        "timings": [
                        ],
                        "children": [
                         {
                           "name": "SEQ_SCAN",
                           "timing":0.035928,
                           "cardinality":3140339,
                           "extra_info": "char_name\n[INFOSEPARATOR]\nname\nid",
                           "timings": [
                           ],
                           "children": [
                           ]
                         }
                        ]
                      }
                     ]
                   }
                  ]
                }
,
                {
                  "name": "HASH_JOIN",
                  "timing":0.000130,
                  "cardinality":85941,
                  "extra_info": "INNER\nstatus_id = id\n",
                  "timings": [
                  ],
                  "children": [
                   {
                     "name": "HASH_JOIN",
                     "timing":0.000209,
                     "cardinality":85941,
                     "extra_info": "INNER\nsubject_id = id\n",
                     "timings": [
                     ],
                     "children": [
                      {
                        "name": "SEQ_SCAN",
                        "timing":0.000061,
                        "cardinality":135086,
                        "extra_info": "complete_cast\n[INFOSEPARATOR]\nmovie_id\nsubject_id\nstatus_id",
                        "timings": [
                        ],
                        "children": [
                        ]
                      }
,
                      {
                        "name": "SEQ_SCAN",
                        "timing":0.000006,
                        "cardinality":1,
                        "extra_info": "comp_cast_type\n[INFOSEPARATOR]\nkind\nid\n[INFOSEPARATOR]\nFilters: kind=cast AND kind IS NOT NULL\n",
                        "timings": [
                        ],
                        "children": [
                        ]
                      }
                     ]
                   }
,
                   {
                     "name": "PROJECTION",
                     "timing":0.000000,
                     "cardinality":2,
                     "extra_info": "#1\n",
                     "timings": [
                     ],
                     "children": [
                      {
                        "name": "FILTER",
                        "timing":0.000001,
                        "cardinality":2,
                        "extra_info": "contains(kind, 'complete')",
                        "timings": [
                        ],
                        "children": [
                         {
                           "name": "SEQ_SCAN",
                           "timing":0.000001,
                           "cardinality":4,
                           "extra_info": "comp_cast_type\n[INFOSEPARATOR]\nkind\nid",
                           "timings": [
                           ],
                           "children": [
                           ]
                         }
                        ]
                      }
                     ]
                   }
                  ]
                }
               ]
             }
            ]
          }
         ]
       }
      ]
    }
   ]
}